Metadata-Version: 1.0
Name: kdata
Version: 0.0.2
Summary: kdata.
Home-page: https://github.com/jungamer/kdata
Author: jungamer
Author-email: 624621566@qq.com
License: MIT
Platform: UNKNOWN
